Metadata-Version: 2.1
Name: request2postman
Version: 0.1.1
Summary: Lib that generates postman collections out of requests
Home-page: https://github.com/Ander813
Download-URL: https://github.com/Ander813/request2postman/archive/refs/tags/0.1.0.tar.gz
Author: Egor Gondurov
Author-email: ander_the_wood@mail.ru
License: MIT
Keywords: requests,postman,generate postman collections
Classifier: Development Status :: 3 - Alpha
Classifier: Intended Audience :: Developers
Classifier: Topic :: Software Development :: Build Tools
Classifier: License :: OSI Approved :: MIT License
Classifier: Programming Language :: Python :: 3
Classifier: Programming Language :: Python :: 3.6
Classifier: Programming Language :: Python :: 3.7
Classifier: Programming Language :: Python :: 3.8
Classifier: Programming Language :: Python :: 3.9
Classifier: Programming Language :: Python :: 3.10
License-File: LICENSE.TXT
